aces/README.md
aces/__init__.py
aces/aggregate.py
aces/config.py
aces/constraints.py
aces/expand_shards.py
aces/extract_subtree.py
aces/predicates.py
aces/query.py
aces/run.py
aces/types.py
aces/utils.py
aces/configs/__init__.py
aces/configs/_aces.yaml
aces/configs/data/defaults.yaml
aces/configs/data/sharded.yaml
aces/configs/data/single_file.yaml
es_aces-0.7.1.dist-info/licenses/LICENSE
es_aces-0.7.1.dist-info/METADATA
es_aces-0.7.1.dist-info/WHEEL
es_aces-0.7.1.dist-info/entry_points.txt
es_aces-0.7.1.dist-info/top_level.txt
es_aces-0.7.1.dist-info/RECORD
