Metadata-Version: 2.4
Name: es-aces
Version: 0.7.1
Summary: ACES: Automatic Cohort Extraction System for Event-Streams
Author-email: Justin Xu <justin13601@hotmail.com>, Matthew McDermott <mattmcdermott8@gmail.com>
Project-URL: Homepage, https://github.com/justin13601/ACES
Project-URL: Issues, https://github.com/justin13601/ACES/issues
Classifier: Programming Language :: Python :: 3
Classifier: License :: OSI Approved :: MIT License
Classifier: Operating System :: OS Independent
Requires-Python: >=3.10
License-File: LICENSE
Requires-Dist: polars~=1.30.0
Requires-Dist: numpy<1.29.0
Requires-Dist: bigtree==0.18.*
Requires-Dist: ruamel.yaml==0.18.*
Requires-Dist: hydra-core~=1.3.2
Requires-Dist: pytimeparse==1.1.*
Requires-Dist: networkx==3.3.*
Requires-Dist: pyarrow
Requires-Dist: meds~=0.4.0
Provides-Extra: dev
Requires-Dist: pre-commit<4; extra == "dev"
Requires-Dist: ruff; extra == "dev"
Provides-Extra: tests
Requires-Dist: pytest; extra == "tests"
Requires-Dist: pytest-cov; extra == "tests"
Requires-Dist: pytest-subtests; extra == "tests"
Requires-Dist: hypothesis; extra == "tests"
Provides-Extra: profiling
Requires-Dist: psutil; extra == "profiling"
Dynamic: license-file
